usuarioAPI1103/__init__.py
usuarioAPI1103/main.py
usuarioAPI1103/controller/__init__.py
usuarioAPI1103/controller/endereco.py
usuarioAPI1103/controller/generic.py
usuarioAPI1103/controller/pessoa.py
usuarioAPI1103/model/__init__.py
usuarioAPI1103/model/dto.py
usuarioAPI1103/model/models.py
usuarioAPI1103/repository/__init__.py
usuarioAPI1103/repository/base.py
usuarioAPI1103/service/__init__.py
usuarioAPI1103/service/base.py
usuarioAPI1103/util/__init__.py
usuarioAPI1103/util/database.py
usuarioapi1103-0.1.1.dist-info/METADATA
usuarioapi1103-0.1.1.dist-info/WHEEL
usuarioapi1103-0.1.1.dist-info/top_level.txt
usuarioapi1103-0.1.1.dist-info/RECORD
