Metadata-Version: 2.4
Name: usuarioAPI1103
Version: 0.1.1
Summary: Biblioteca de criação de contas de usuarios com fastapi.
Home-page: https://github.com/gffiorot/usuarioAPI
Author: Gustavo Firme Fiorot
Author-email: gffiorot@gmail.com
Classifier: Programming Language :: Python :: 3
Classifier: License :: OSI Approved :: MIT License
Classifier: Operating System :: OS Independent
Requires-Python: >=3.8
Requires-Dist: fastapi
Requires-Dist: uvicorn
Requires-Dist: sqlmodel
Requires-Dist: pydantic
Requires-Dist: python-dotenv
Requires-Dist: email-validator
Dynamic: author
Dynamic: author-email
Dynamic: classifier
Dynamic: description
Dynamic: description-content-type
Dynamic: home-page
Dynamic: requires-dist
Dynamic: requires-python
Dynamic: summary
